{
  "parent": "minecraft:recipes/root",
  "criteria": {
    "has_minecraft:bamboo_door": {
      "conditions": {
        "items": [
          {
            "items": "minecraft:bamboo_door"
          }
        ]
      },
      "trigger": "minecraft:inventory_changed"
    },
    "has_the_recipe": {
      "conditions": {
        "recipe": "tuttasdoors:crafting/indiscrete_from_normal_bamboo"
      },
      "trigger": "minecraft:recipe_unlocked"
    }
  },
  "requirements": [
    [
      "has_the_recipe",
      "has_minecraft:bamboo_door"
    ]
  ],
  "rewards": {
    "recipes": [
      "tuttasdoors:crafting/indiscrete_from_normal_bamboo"
    ]
  }
}